maap_che_sidebar_visibility_jupyter_extension/__init__.py
maap_che_sidebar_visibility_jupyter_extension/_version.py
maap_che_sidebar_visibility_jupyter_extension-1.1.3.data/data/share/jupyter/labextensions/maap_che_sidebar_visibility_jupyter_extension/package.json
maap_che_sidebar_visibility_jupyter_extension-1.1.3.data/data/share/jupyter/labextensions/maap_che_sidebar_visibility_jupyter_extension/static/509.33cf4a9ce57ee10d57e1.js
maap_che_sidebar_visibility_jupyter_extension-1.1.3.data/data/share/jupyter/labextensions/maap_che_sidebar_visibility_jupyter_extension/static/728.7319121760e83a5a16c2.js
maap_che_sidebar_visibility_jupyter_extension-1.1.3.data/data/share/jupyter/labextensions/maap_che_sidebar_visibility_jupyter_extension/static/remoteEntry.bb1c8061073f0d10d4e8.js
maap_che_sidebar_visibility_jupyter_extension-1.1.3.data/data/share/jupyter/labextensions/maap_che_sidebar_visibility_jupyter_extension/static/style.js
maap_che_sidebar_visibility_jupyter_extension-1.1.3.data/data/share/jupyter/labextensions/maap_che_sidebar_visibility_jupyter_extension/static/third-party-licenses.json
maap_che_sidebar_visibility_jupyter_extension-1.1.3.data/data/share/jupyter/labextensions/maap_che_sidebar_visibility_jupyter_extension/install.json
maap_che_sidebar_visibility_jupyter_extension-1.1.3.dist-info/METADATA
maap_che_sidebar_visibility_jupyter_extension-1.1.3.dist-info/WHEEL
maap_che_sidebar_visibility_jupyter_extension-1.1.3.dist-info/licenses/LICENSE
maap_che_sidebar_visibility_jupyter_extension-1.1.3.dist-info/RECORD
