Metadata-Version: 2.4
Name: maap_che_sidebar_visibility_jupyter_extension
Version: 1.1.3
Dynamic: Keywords
Summary: A Jupyter extension that provides users the ability to hide the Eclipse Che sidebar in the MAAP ADE.
Project-URL: Homepage, https://github.com/MAAP-Project/che-sidebar-visibility-jupyter-extension
Project-URL: Bug Tracker, https://github.com/MAAP-Project/che-sidebar-visibility-jupyter-extension/issues
Project-URL: Repository, https://github.com/MAAP-Project/che-sidebar-visibility-jupyter-extension.git
Author-email: Anil Natha <anil.natha@jpl.nasa.gov>
License:                                  Apache License
License-File: LICENSE
Classifier: Framework :: Jupyter
Classifier: Framework :: Jupyter :: JupyterLab
Classifier: Framework :: Jupyter :: JupyterLab :: 4
Classifier: Framework :: Jupyter :: JupyterLab :: Extensions
Classifier: Framework :: Jupyter :: JupyterLab :: Extensions :: Prebuilt
Classifier: License :: OSI Approved :: Apache Software License
Classifier: Programming Language :: Python
Classifier: Programming Language :: Python :: 3
Classifier: Programming Language :: Python :: 3.7
Classifier: Programming Language :: Python :: 3.8
Classifier: Programming Language :: Python :: 3.9
Classifier: Programming Language :: Python :: 3.10
Classifier: Programming Language :: Python :: 3.11
Requires-Python: >=3.8
